CHANGES.rst
MANIFEST.in
README.rst
setup.py
StoneageHTML.egg-info/PKG-INFO
StoneageHTML.egg-info/SOURCES.txt
StoneageHTML.egg-info/dependency_links.txt
StoneageHTML.egg-info/not-zip-safe
StoneageHTML.egg-info/requires.txt
StoneageHTML.egg-info/top_level.txt
docs/INSTALL.txt
docs/LICENSE.txt
stoneagehtml/__init__.py
stoneagehtml/stoneagehtml.py