Metadata-Version: 2.1
Name: StoneageHTML
Version: 1.0.0
Summary: Stone-Age HTML Filter: prepare documents for e-mail distribution
Home-page: http://github.com/collective/stoneagehtml
Author: Malthe Borch
Author-email: mborch@gmail com
Maintainer: Johannes Raggam
Maintainer-email: raggam-nl@adm.at
License: LGPL - http://www.gnu.org/copyleft/lesser.html
Keywords: mail css
Platform: UNKNOWN
Classifier: Development Status :: 4 - Beta
Classifier: Environment :: Web Environment
Classifier: Intended Audience :: Developers
Classifier: License :: OSI Approved :: GNU Library or Lesser General Public License (LGPL)
Classifier: Operating System :: OS Independent
Classifier: Programming Language :: Python
Classifier: Programming Language :: Python :: 2.7
Classifier: Programming Language :: Python :: 3.7
Classifier: Programming Language :: Python :: 3.8
Classifier: Topic :: Internet
Classifier: Topic :: Software Development :: Libraries :: Python Modules
Classifier: Topic :: Text Processing :: Markup :: HTML
Provides-Extra: test
